eprints2archives/__init__.py
eprints2archives/__main__.py
eprints2archives/auth.py
eprints2archives/eprints.py
eprints2archives/exceptions.py
eprints2archives/exit_codes.py
eprints2archives/main_body.py
eprints2archives/run_manager.py
eprints2archives/services/__init__.py
eprints2archives/services/archivetoday.py
eprints2archives/services/base.py
eprints2archives/services/internetarchive.py
eprints2archives/services/timemap.py
eprints2archives/services/upload_status.py
eprints2archives-1.3.5.data/scripts/eprints2archives
eprints2archives-1.3.5.dist-info/LICENSE
eprints2archives-1.3.5.dist-info/METADATA
eprints2archives-1.3.5.dist-info/WHEEL
eprints2archives-1.3.5.dist-info/entry_points.txt
eprints2archives-1.3.5.dist-info/top_level.txt
eprints2archives-1.3.5.dist-info/RECORD
