Metadata-Version: 2.1
Name: eprints2archives
Version: 1.3.5
Summary: Send EPrints URLs to the Internet Archive and other archives
Home-page: https://github.com/caltechlibrary/eprints2archives
Author: Michael Hucka
Author-email: mhucka@caltech.edu
License: BSD 3-clause
Project-URL: Source Code, https://github.com/caltechlibrary/eprints2archives
Project-URL: Bug Tracker, https://github.com/caltechlibrary/eprints2archives/issues
Keywords: EPrints,archives,web archives,preservation
Classifier: Development Status :: 5 - Production/Stable
Classifier: Environment :: Console
Classifier: Intended Audience :: Science/Research
Classifier: Intended Audience :: Information Technology
Classifier: Intended Audience :: System Administrators
Classifier: License :: OSI Approved :: BSD License
Classifier: Operating System :: MacOS :: MacOS X
Classifier: Operating System :: Microsoft :: Windows
Classifier: Operating System :: POSIX
Classifier: Operating System :: POSIX :: Linux
Classifier: Operating System :: Unix
Classifier: Programming Language :: Python
Classifier: Programming Language :: Python :: 3.6
Classifier: Topic :: System :: Archiving
Classifier: Topic :: Utilities
Requires-Python: >=3.6
License-File: LICENSE
Requires-Dist: aenum (>=3.1.0)
Requires-Dist: appdirs (>=1.4.4)
Requires-Dist: bun (>=0.0.8)
Requires-Dist: commonpy (==1.10.0)
Requires-Dist: cssselect (>=1.1.0)
Requires-Dist: dateparser (>=1.0.0)
Requires-Dist: h2 (>=3.2.0)
Requires-Dist: httpx (==0.23.0)
Requires-Dist: humanize (>=3.14.0)
Requires-Dist: keyring (>=23.2.1)
Requires-Dist: keyrings.alt (>=4.1.0)
Requires-Dist: lxml (>=4.8.0)
Requires-Dist: plac (>=1.3.4)
Requires-Dist: pydash (>=5.1.0)
Requires-Dist: pypubsub (>=4.0.3)
Requires-Dist: python-dateutil (>=2.8.2)
Requires-Dist: rich (==12.2.0)
Requires-Dist: setuptools (>=62.1.0)
Requires-Dist: sidetrack (>=2.0.1)
Requires-Dist: stopit (>=1.1.2)
Requires-Dist: tldextract (>=3.0.2)
Requires-Dist: urllib3 (>=1.26.5)
Requires-Dist: validators (>=0.18.2)
Requires-Dist: typing-extensions (>=4.2.0)
